setup.py
anect/__init__.py
anect/anect_run.py
anect.egg-info/PKG-INFO
anect.egg-info/SOURCES.txt
anect.egg-info/dependency_links.txt
anect.egg-info/entry_points.txt
anect.egg-info/requires.txt
anect.egg-info/top_level.txt