Metadata-Version: 2.1
Name: anect
Version: 1.0.5
Summary: ane converter
Author: Eileen Yoon
Author-email: eyn@gmx.com
